Voting Machine/project_1/project_1.srcs/sources_1/new/design.v
`timescale 1ns / 1ps

// Button Control


module ButtonControl(
    input CLK,  // CLK
    input RST,  // RST
    input BTN,  // BTN
    output reg VALID_VOTE // Valid Vote
    );
    
    reg[30:0] COUNTER; // Counts Number of votes
    
    always @(posedge CLK)
    begin
        if (RST)
            COUNTER <= 0;   // Resets Counter to zero when Reset is 0
        else
        begin
            if (BTN & COUNTER < 11)
                COUNTER <= COUNTER + 1;   // Adds till 10
            else if (!BTN)
                COUNTER <= 0;   // Resets Counter to zero if Button is not pushed
        end
     end
     
     always @(posedge CLK)
     begin
        if (RST)
            VALID_VOTE <= 1'b0;   // Resets Vote to zero
        else
        begin
            if (COUNTER == 10)
                VALID_VOTE <= 1'b1;    // Set Vote to 1 when counter reaches 10
            else
                VALID_VOTE <= 1'b0;     // Resets Vote to zero
        end
     end         
endmodule

module ModeControl (
    input CLK,  // CLK
    input RST,  // RST
    input MODE, // MODE
    input VALID_VOTE_CASTED,    // Valid vote casted
    input [7:0] CAND1_VOTE,     // Candidate 1 vote
    input [7:0] CAND2_VOTE,     // Candidate 2 vote
    input [7:0] CAND3_VOTE,     // Candidate 3 vote
    input [7:0] CAND4_VOTE,     // Candidate 4 vote
    input CAND1_BTN_PRESS,      // Candidate 1 vote button
    input CAND2_BTN_PRESS,      // Candidate 2 vote button
    input CAND3_BTN_PRESS,      // Candidate 3 vote button
    input CAND4_BTN_PRESS,      // Candidate 4 vote button
    output reg [7:0] LEDS       // LEDS
);
    reg [30:0] COUNTER;     // Counter
    
    always @(posedge CLK)
    begin
        if(RST)
            COUNTER <=0; // Whenever reset is pressed counter starts from 0
        else if (VALID_VOTE_CASTED)
            COUNTER <= COUNTER + 1; // If valid vote is casted, counter adds 1
        else if (COUNTER != 0 & COUNTER < 10)
            COUNTER <= COUNTER + 1; // If counter is not 0 increase it till 10
        else
            COUNTER <= 0; // Once counter becomes 10, reset it to zero
     end 
   
   always @(posedge CLK)
   begin
      if(RST)
          LEDS <= 0;
      else
      begin
        if(MODE == 0 & COUNTER > 0) // Mode0 -> Voting mode, Mode1 -> Result Mode
            LEDS <= 8'hFF;
        else if (MODE == 0)
            LEDS <= 8'H00;
        else if (MODE == 1) // Result Mode
        begin
            if (CAND1_BTN_PRESS)
                LEDS <= CAND1_VOTE;
            else if (CAND2_BTN_PRESS)
                LEDS <= CAND2_VOTE;
            else if (CAND3_BTN_PRESS)
                LEDS <= CAND3_VOTE;
            else if (CAND4_BTN_PRESS)
                LEDS <= CAND4_VOTE;
         end
        end
     end
endmodule

module VoteLogger (
    input CLK,
    input RST,
    input MODE,
    input CAND1_VOTE_VALID,
    input CAND2_VOTE_VALID,
    input CAND3_VOTE_VALID,
    input CAND4_VOTE_VALID,
    output reg [7:0] CAND1_VOTE_RCVD,
    output reg [7:0] CAND2_VOTE_RCVD,
    output reg [7:0] CAND3_VOTE_RCVD,
    output reg [7:0] CAND4_VOTE_RCVD
    );
    
    always @(posedge CLK)
    begin
        if (RST)
        begin
            CAND1_VOTE_RCVD <= 0;
            CAND2_VOTE_RCVD <= 0;
            CAND3_VOTE_RCVD <= 0;
            CAND4_VOTE_RCVD <= 0;
        end 
        else
        begin
            if(CAND1_VOTE_VALID & MODE == 0)
                CAND1_VOTE_RCVD <= CAND1_VOTE_RCVD + 1;
            else if(CAND2_VOTE_VALID & MODE == 0)
                CAND2_VOTE_RCVD <= CAND2_VOTE_RCVD + 1;
            else if(CAND3_VOTE_VALID & MODE == 0)
                CAND3_VOTE_RCVD <= CAND3_VOTE_RCVD + 1;
            else if(CAND4_VOTE_VALID & MODE == 0)
                CAND4_VOTE_RCVD <= CAND4_VOTE_RCVD + 1;
        end
     end  
endmodule

module VotingMachine(
    input CLK,
    input RST,
    input MODE,
    input BTN1,
    input BTN2,
    input BTN3,
    input BTN4,
    output [7:0] LEDS
);

    wire VALID_VOTE_1;
    wire VALID_VOTE_2;
    wire VALID_VOTE_3;
    wire VALID_VOTE_4;
    wire [7:0] CAND1_VOTE_RCVD;
    wire [7:0] CAND2_VOTE_RCVD;
    wire [7:0] CAND3_VOTE_RCVD;
    wire [7:0] CAND4_VOTE_RCVD;
    wire ANYVALIDVOTE;
    
    assign ANYVALIDVOTE = VALID_VOTE_1 | VALID_VOTE_2 | VALID_VOTE_3 | VALID_VOTE_4;
    
    ButtonControl BC1(
        CLK, 
        RST,
        BTN,
        VALID_VOTE_1
    );
    
    ButtonControl BC2(
        CLK, 
        RST,
        BTN,
        VALID_VOTE_2
    );
    
    ButtonControl BC3(
        CLK, 
        RST,
        BTN,
        VALID_VOTE_3
    );
    
    ButtonControl BC4(
        CLK, 
        RST,
        BTN,
        VALID_VOTE_4
    );
    
    VoteLogger VL(
        CLK,
        RST,
        MODE,
        VALID_VOTE_1,
        VALID_VOTE_2,
        VALID_VOTE_3,
        VALID_VOTE_4,
        CAND1_VOTE_RCVD,
        CAND2_VOTE_RCVD,
        CAND3_VOTE_RCVD,
        CAND4_VOTE_RCVD
    );
    
    ModeControl MC(
        CLK,
        RST,
        MODE,
        VALID_VOTE_CASTED,
        CAND1_VOTE_RCVD,
        CAND2_VOTE_RCVD,
        CAND3_VOTE_RCVD,
        CAND4_VOTE_RCVD,
        VALID_VOTE_1,
        VALID_VOTE_2,
        VALID_VOTE_3,
        VALID_VOTE_4,
        LEDS
    );


endmodule

Voting Machine/project_1/project_1.srcs/sources_1/new/VotingMachine_tb.v
`timescale 1ns / 1ps


module test;

    // inputs
    reg CLK;
    reg RST;
    reg MODE;
    reg BTN1;
    reg BTN2;
    reg BTN3;
    reg BTN4;
    
    // outputs
    wire [7:0] LEDS;
    
    // Instantiate the Design Under Test
    
    VotingMachine DUT(
        CLK,
        RST,
        MODE,
        BTN1,
        BTN2,
        BTN3,
        BTN4,
        LEDS
    );
    
    initial
        begin
            CLK = 0;
            forever #5 CLK = ~CLK;
        end
        
        initial begin
            // Initialize Inputs
            RST = 1; MODE = 0; BTN1 = 0; BTN2 = 0; BTN3 = 0; BTN4 = 0;
            // Wait 100 ns for global reset to finish
            #100;
            
            // Add stimulus here
            
            #100; RST = 0; MODE = 0; BTN1 = 0; BTN2 = 0; BTN3 = 0; BTN4 = 0;
            #5;   RST = 0; MODE = 0; BTN1 = 1; BTN2 = 0; BTN3 = 0; BTN4 = 0;
            #10; RST = 0; MODE = 0; BTN1 = 0; BTN2 = 0; BTN3 = 0; BTN4 = 0;
            #5;   RST = 0; MODE = 0; BTN1 = 1; BTN2 = 0; BTN3 = 0; BTN4 = 0;
            #200; RST = 0; MODE = 0; BTN1 = 0; BTN2 = 0; BTN3 = 0; BTN4 = 0;
            #5;   RST = 0; MODE = 0; BTN1 = 0; BTN2 = 0; BTN3 = 0; BTN4 = 0;
            #10; RST = 0; MODE = 0; BTN1 = 0; BTN2 = 0; BTN3 = 0; BTN4 = 0;
            #5;   RST = 0; MODE = 0; BTN1 = 0; BTN2 = 0; BTN3 = 0; BTN4 = 0;
            
            #5; RST = 0; MODE = 0; BTN1 = 0; BTN2 = 1; BTN3 = 0; BTN4 = 0;
            #200;   RST = 0; MODE = 0; BTN1 = 0; BTN2 = 0; BTN3 = 0; BTN4 = 0;
            #5;   RST = 0; MODE = 0; BTN1 = 0; BTN2 = 0; BTN3 = 0; BTN4 = 0;
            #10; RST = 0; MODE = 0; BTN1 = 0; BTN2 = 0; BTN3 = 0; BTN4 = 0;
            #5;   RST = 0; MODE = 0; BTN1 = 0; BTN2 = 0; BTN3 = 0; BTN4 = 0;
            
            #5; RST = 0; MODE = 0; BTN1 = 0; BTN2 = 1; BTN3 = 1; BTN4 = 0;
            #200;   RST = 0; MODE = 0; BTN1 = 0; BTN2 = 0; BTN3 = 0; BTN4 = 0;
            #5;   RST = 0; MODE = 0; BTN1 = 0; BTN2 = 0; BTN3 = 0; BTN4 = 0;
            #10; RST = 0; MODE = 0; BTN1 = 0; BTN2 = 0; BTN3 = 0; BTN4 = 0;
            #5;   RST = 0; MODE = 0; BTN1 = 0; BTN2 = 0; BTN3 = 0; BTN4 = 0;
            
            #5; RST = 0; MODE = 1; BTN1 = 0; BTN2 = 1; BTN3 = 0; BTN4 = 0;
            #200;   RST = 0; MODE = 1; BTN1 = 0; BTN2 = 0; BTN3 = 1; BTN4 = 0;
            #5;   RST = 0; MODE = 0; BTN1 = 0; BTN2 = 0; BTN3 = 0; BTN4 = 0;
            #10; RST = 0; MODE = 0; BTN1 = 0; BTN2 = 0; BTN3 = 0; BTN4 = 0;
            #5;   RST = 0; MODE = 0; BTN1 = 0; BTN2 = 0; BTN3 = 0; BTN4 = 0;
            
            #5; RST = 0; MODE = 0; BTN1 = 0; BTN2 = 0; BTN3 = 1; BTN4 = 0;
            #200;   RST = 0; MODE = 0; BTN1 = 0; BTN2 = 0; BTN3 = 0; BTN4 = 0;
            #5;   RST = 0; MODE = 0; BTN1 = 0; BTN2 = 0; BTN3 = 0; BTN4 = 0;
            #10; RST = 0; MODE = 0; BTN1 = 0; BTN2 = 0; BTN3 = 0; BTN4 = 0;
            #5;   RST = 0; MODE = 0; BTN1 = 0; BTN2 = 0; BTN3 = 0; BTN4 = 0;
            
            $finish;
        end
        
        initial
            begin
            $dumpvars;
                $dumpfile("dump.vcd");
            
            end
        initial
            $monitor($time, "mode=%b, button1=%b, button2=%b, button3=%b, button4=%b, led=%d", MODE, BTN1, BTN2, BTN3, BTN4,LEDS);
endmodule

Voting Machine/project_1/project_1.sim/sim_1/behav/xsim/dump.vcd
$date
   Thu Jan 22 13:06:54 2026
$end

$version
  2025.2
$end

$timescale
  1ps
$end

$scope module test $end
$var reg 1 ! CLK $end
$var reg 1 " RST $end
$var reg 1 # MODE $end
$var reg 1 $ BTN1 $end
$var reg 1 % BTN2 $end
$var reg 1 & BTN3 $end
$var reg 1 ' BTN4 $end
$var wire 8 ( LEDS [7:0] $end
$scope module DUT $end
$var wire 1 ) CLK $end
$var wire 1 * RST $end
$var wire 1 + MODE $end
$var wire 1 , BTN1 $end
$var wire 1 - BTN2 $end
$var wire 1 . BTN3 $end
$var wire 1 / BTN4 $end
$var wire 8 ( LEDS [7:0] $end
$var wire 1 0 VALID_VOTE_1 $end
$var wire 1 1 VALID_VOTE_2 $end
$var wire 1 2 VALID_VOTE_3 $end
$var wire 1 3 VALID_VOTE_4 $end
$var wire 8 4 CAND1_VOTE_RCVD [7:0] $end
$var wire 8 5 CAND2_VOTE_RCVD [7:0] $end
$var wire 8 6 CAND3_VOTE_RCVD [7:0] $end
$var wire 8 7 CAND4_VOTE_RCVD [7:0] $end
$var wire 1 8 ANYVALIDVOTE $end
$var wire 1 9 BTN $end
$var wire 1 : VALID_VOTE_CASTED $end
$scope module BC1 $end
$var wire 1 ) CLK $end
$var wire 1 * RST $end
$var wire 1 9 BTN $end
$var reg 1 ; VALID_VOTE $end
$var reg 31 < COUNTER [30:0] $end
$upscope $end
$scope module BC2 $end
$var wire 1 ) CLK $end
$var wire 1 * RST $end
$var wire 1 9 BTN $end
$var reg 1 = VALID_VOTE $end
$var reg 31 > COUNTER [30:0] $end
$upscope $end
$scope module BC3 $end
$var wire 1 ) CLK $end
$var wire 1 * RST $end
$var wire 1 9 BTN $end
$var reg 1 ? VALID_VOTE $end
$var reg 31 @ COUNTER [30:0] $end
$upscope $end
$scope module BC4 $end
$var wire 1 ) CLK $end
$var wire 1 * RST $end
$var wire 1 9 BTN $end
$var reg 1 A VALID_VOTE $end
$var reg 31 B COUNTER [30:0] $end
$upscope $end
$scope module VL $end
$var wire 1 ) CLK $end
$var wire 1 * RST $end
$var wire 1 + MODE $end
$var wire 1 0 CAND1_VOTE_VALID $end
$var wire 1 1 CAND2_VOTE_VALID $end
$var wire 1 2 CAND3_VOTE_VALID $end
$var wire 1 3 CAND4_VOTE_VALID $end
$var reg 8 C CAND1_VOTE_RCVD [7:0] $end
$var reg 8 D CAND2_VOTE_RCVD [7:0] $end
$var reg 8 E CAND3_VOTE_RCVD [7:0] $end
$var reg 8 F CAND4_VOTE_RCVD [7:0] $end
$upscope $end
$scope module MC $end
$var wire 1 ) CLK $end
$var wire 1 * RST $end
$var wire 1 + MODE $end
$var wire 1 : VALID_VOTE_CASTED $end
$var wire 8 4 CAND1_VOTE [7:0] $end
$var wire 8 5 CAND2_VOTE [7:0] $end
$var wire 8 6 CAND3_VOTE [7:0] $end
$var wire 8 7 CAND4_VOTE [7:0] $end
$var wire 1 0 CAND1_BTN_PRESS $end
$var wire 1 1 CAND2_BTN_PRESS $end
$var wire 1 2 CAND3_BTN_PRESS $end
$var wire 1 3 CAND4_BTN_PRESS $end
$var reg 8 G LEDS [7:0] $end
$var reg 31 H COUNTER [30:0] $end
$upscope $end
$upscope $end
$upscope $end
$enddefinitions $end

#0
$dumpvars
0!
1"
0#
0$
0%
0&
0'
bx (
0)
1*
0+
0,
0-
0.
0/
x0
x1
x2
x3
bx 4
bx 5
bx 6
bx 7
x8
z9
z:
x;
bx <
x=
bx >
x?
bx @
xA
bx B
bx C
bx D
bx E
bx F
bx G
bx H
$end

#5000
1!
b0 (
1)
00
01
02
03
b0 4
b0 5
b0 6
b0 7
08
0;
b0 <
0=
b0 >
0?
b0 @
0A
b0 B
b0 C
b0 D
b0 E
b0 F
b0 G
b0 H

#10000
0!
0)

#15000
1!
1)

#20000
0!
0)

#25000
1!
1)

#30000
0!
0)

#35000
1!
1)

#40000
0!
0)

#45000
1!
1)

#50000
0!
0)

#55000
1!
1)

#60000
0!
0)

#65000
1!
1)

#70000
0!
0)

#75000
1!
1)

#80000
0!
0)

#85000
1!
1)

#90000
0!
0)

#95000
1!
1)

#100000
0!
0)

#105000
1!
1)

#110000
0!
0)

#115000
1!
1)

#120000
0!
0)

#125000
1!
1)

#130000
0!
0)

#135000
1!
1)

#140000
0!
0)

#145000
1!
1)

#150000
0!
0)

#155000
1!
1)

#160000
0!
0)

#165000
1!
1)

#170000
0!
0)

#175000
1!
1)

#180000
0!
0)

#185000
1!
1)

#190000
0!
0)

#195000
1!
1)

#200000
0!
0"
0)
0*

#205000
1!
1$
1)
1,

#210000
0!
0)

#215000
1!
0$
1)
0,

#220000
0!
1$
0)
1,

#225000
1!
1)

#230000
0!
0)

#235000
1!
1)

#240000
0!
0)

#245000
1!
1)

#250000
0!
0)

#255000
1!
1)

#260000
0!
0)

#265000
1!
1)

#270000
0!
0)

#275000
1!
1)

#280000
0!
0)

#285000
1!
1)

#290000
0!
0)

#295000
1!
1)

#300000
0!
0)

#305000
1!
1)

#310000
0!
0)

#315000
1!
1)

#320000
0!
0)

#325000
1!
1)

#330000
0!
0)

#335000
1!
1)

#340000
0!
0)

#345000
1!
1)

#350000
0!
0)

#355000
1!
1)

#360000
0!
0)

#365000
1!
1)

#370000
0!
0)

#375000
1!
1)

#380000
0!
0)

#385000
1!
1)

#390000
0!
0)

#395000
1!
1)

#400000
0!
0)

#405000
1!
1)

#410000
0!
0)

#415000
1!
1)

#420000
0!
0$
0)
0,

#425000
1!
1)

#430000
0!
0)

#435000
1!
1)

#440000
0!
0)

#445000
1!
1%
1)
1-

#450000
0!
0)

#455000
1!
1)

#460000
0!
0)

#465000
1!
1)

#470000
0!
0)

#475000
1!
1)

#480000
0!
0)

#485000
1!
1)

#490000
0!
0)

#495000
1!
1)

#500000
0!
0)

#505000
1!
1)

#510000
0!
0)

#515000
1!
1)

#520000
0!
0)

#525000
1!
1)

#530000
0!
0)

#535000
1!
1)

#540000
0!
0)

#545000
1!
1)

#550000
0!
0)

#555000
1!
1)

#560000
0!
0)

#565000
1!
1)

#570000
0!
0)

#575000
1!
1)

#580000
0!
0)

#585000
1!
1)

#590000
0!
0)

#595000
1!
1)

#600000
0!
0)

#605000
1!
1)

#610000
0!
0)

#615000
1!
1)

#620000
0!
0)

#625000
1!
1)

#630000
0!
0)

#635000
1!
1)

#640000
0!
0)

#645000
1!
0%
1)
0-

#650000
0!
0)

#655000
1!
1)

#660000
0!
0)

#665000
1!
1)

#670000
0!
1%
1&
0)
1-
1.

#675000
1!
1)

#680000
0!
0)

#685000
1!
1)

#690000
0!
0)

#695000
1!
1)

#700000
0!
0)

#705000
1!
1)

#710000
0!
0)

#715000
1!
1)

#720000
0!
0)

#725000
1!
1)

#730000
0!
0)

#735000
1!
1)

#740000
0!
0)

#745000
1!
1)

#750000
0!
0)

#755000
1!
1)

#760000
0!
0)

#765000
1!
1)

#770000
0!
0)

#775000
1!
1)

#780000
0!
0)

#785000
1!
1)

#790000
0!
0)

#795000
1!
1)

#800000
0!
0)

#805000
1!
1)

#810000
0!
0)

#815000
1!
1)

#820000
0!
0)

#825000
1!
1)

#830000
0!
0)

#835000
1!
1)

#840000
0!
0)

#845000
1!
1)

#850000
0!
0)

#855000
1!
1)

#860000
0!
0)

#865000
1!
1)

#870000
0!
0%
0&
0)
0-
0.

#875000
1!
1)

#880000
0!
0)

#885000
1!
1)

#890000
0!
0)

#895000
1!
1#
1%
1)
1+
1-

